[
  {
    "id": 1,
    "title": "Clean Architecture: A Craftsman's Guide to Software Structure and Design",
    "author_fullname": "Robert Martin",
    "publish_date": "Sep 17, 2017",
    "price": "$32",
    "cover_url": "http://localhost:4242/images/1.jpg"
  },
  {
    "id": 2,
    "title": "Clean Code: A Handbook of Agile Software Craftsmanship",
    "author_fullname": "Robert Martin",
    "publish_date": "Aug 11, 2008",
    "price": "$41",
    "cover_url": "http://localhost:4242/images/2.jpg"
  },
  {
    "id": 3,
    "title": "Effective TypeScript: 62 Specific Ways to Improve Your TypeScript",
    "author_fullname": "Dan Vanderkam",
    "publish_date": "Nov 12, 2019",
    "price": "$24",
    "cover_url": "http://localhost:4242/images/3.jpg"
  },
  {
    "id": 4,
    "title": "JavaScript: The Definitive Guide: Master the World's Most-Used Programming Language",
    "author_fullname": "David Flanagan",
    "publish_date": "Jun 23, 2020",
    "price": "$29",
    "cover_url": "http://localhost:4242/images/4.jpg"
  },
  {
    "id": 5,
    "title": "Programming in Haskell",
    "author_fullname": "Graham Hutton",
    "publish_date": "Sep 1, 2016",
    "price": "$37",
    "cover_url": "http://localhost:4242/images/5.jpg"
  },
  {
    "id": 6,
    "title": "Real World Haskell",
    "author_fullname": "Bryan O'Sullivan, John Goerzen",
    "publish_date": "Dec 1, 2008",
    "price": "$28",
    "cover_url": "http://localhost:4242/images/6.jpg"
  },
  {
    "id": 7,
    "title": "Building Microservices: Designing Fine-Grained Systems",
    "author_fullname": "Sam Newman",
    "publish_date": "Sep 28, 2021",
    "price": "$46",
    "cover_url": "http://localhost:4242/images/7.jpg"
  },
  {
    "id": 8,
    "title": "Python Crash Course, 2nd Edition: A Hands-On, Project-Based Introduction to Programming",
    "author_fullname": "Eric Matthes",
    "publish_date": "May 3, 2019",
    "price": "$23",
    "cover_url": "http://localhost:4242/images/8.jpg"
  },
  {
    "id": 9,
    "title": "Learning Redux: Write maintainable, consistent, and easy-to-test web applications",
    "author_fullname": "Daniel Bugl ",
    "publish_date": "Aug 31, 2017",
    "price": "$31",
    "cover_url": "http://localhost:4242/images/9.jpg"
  }
]